imu/Cargo.toml
imu/__init__.py
imu/bindings.cpython-311-s390x-linux-gnu.so
imu/py.typed
imu/requirements-dev.txt
imu/requirements.txt
imu/bindings/Cargo.toml
imu/bindings/src/lib.rs
imu/drivers/bmi088/Cargo.toml
imu/drivers/bmi088/src/lib.rs
imu/drivers/bmi088/src/registers.rs
imu/drivers/bmi088/src/bin/read_bmi088.rs
imu/drivers/bno055/Cargo.toml
imu/drivers/bno055/src/lib.rs
imu/drivers/bno055/src/registers.rs
imu/drivers/bno055/src/bin/read_bno055.rs
imu/drivers/hexmove/Cargo.toml
imu/drivers/hexmove/src/lib.rs
imu/drivers/hexmove/src/bin/read_hexmove.rs
imu/drivers/hiwonder/Cargo.toml
imu/drivers/hiwonder/hiwonder_macros/Cargo.toml
imu/drivers/hiwonder/hiwonder_macros/src/lib.rs
imu/drivers/hiwonder/src/frame.rs
imu/drivers/hiwonder/src/lib.rs
imu/drivers/hiwonder/src/register.rs
imu/drivers/hiwonder/src/bin/read_hiwonder.rs
imu/drivers/hiwonder/src/bin/read_params.rs
imu/imu-traits/Cargo.toml
imu/imu-traits/src/lib.rs
imu/src/lib.rs
imu_py.libs/libattr-b5d4dbc1.so.1.1.0
imu_py.libs/libbz2-c25b28bb.so.1.0.6
imu_py.libs/libcap-fdb91767.so.2.22
imu_py.libs/libdw-0-d2936eb8.176.so
imu_py.libs/libelf-0-3f67317b.176.so
imu_py.libs/liblzma-6229edf4.so.5.2.2
imu_py.libs/libudev-3e2a7877.so.1.6.2
imu_py-0.7.4.dist-info/METADATA
imu_py-0.7.4.dist-info/WHEEL
imu_py-0.7.4.dist-info/top_level.txt
imu_py-0.7.4.dist-info/RECORD
imu_py-0.7.4.dist-info/licenses/LICENSE
